setup.py
hongfei_test/__init__.py
hongfei_test/test.py
hongfei_test.egg-info/PKG-INFO
hongfei_test.egg-info/SOURCES.txt
hongfei_test.egg-info/dependency_links.txt
hongfei_test.egg-info/requires.txt
hongfei_test.egg-info/top_level.txt