Metadata-Version: 2.1
Name: hongfei-test
Version: 0.0.3
Summary: a library for test
Home-page: https://github.com/test/test
Author: hongfei
Author-email: hongfei@gmail.com
License: MIT License
Keywords: test
Platform: any
